{
  "schemaVersion": "4.0.0-feedback-cues",
  "authority": "subscriber-only",
  "routing": "gameplay event -> visual + UI + audio + haptic",
  "invariants": [
    "A cue cannot emit gameplay events, change collision, grant evidence, choose weather or advance narrative state.",
    "Missing audio or haptic capability cannot delay the authoritative event.",
    "Reduced motion and flash-off preserve cue start tick, cue end tick and input return tick.",
    "Every critical audio cue has a non-audio counterpart."
  ],
  "cues": [
    {"id":"cue.flower.quiet","event":"flower.band.enter.quiet","visual":"flower quiet breath","ui":"flower bar notch 1","audio":"sfx.flower_breathe","haptic":"none"},
    {"id":"cue.flower.middle","event":"flower.band.enter.middle","visual":"flower aperture mid resonance; nearby witness chest follows half-time","ui":"flower bar middle gap","audio":"sfx.flower_resonance","haptic":"soft 18ms"},
    {"id":"cue.flower.loud","event":"flower.band.enter.loud","visual":"exposure edge; cables become legible","ui":"flower bar exposed cap","audio":"sfx.flower_exposure","haptic":"soft 12ms"},
    {"id":"cue.gaze.acquire","event":"gaze.acquire","visual":"one-pixel clamp brackets","ui":"read bar appears","audio":"sfx.gaze_acquire","haptic":"medium 24ms"},
    {"id":"cue.gaze.clamp","event":"gaze.clamp.begin","visual":"flower closes asymmetrically","ui":"forced marker on flower bar","audio":"sfx.flower_clamp","haptic":"medium 36ms"},
    {"id":"cue.gaze.hold","event":"gaze.clamp.pulse","visual":"no flash; clamp bracket advances one pixel","ui":"read pressure tick","audio":"sfx.gaze_hold_pulse","haptic":"soft 12ms, minimum interval 700ms"},
    {"id":"cue.gaze.release","event":"gaze.clamp.release","visual":"brackets release before flower recovery","ui":"read bar empties","audio":"sfx.gaze_release","haptic":"none"},
    {"id":"cue.flower.recover","event":"flower.recovery.complete","visual":"petal returns on delayed beat","ui":"forced marker clears","audio":"sfx.flower_recover","haptic":"soft 10ms"},
    {"id":"cue.graze","event":"graze.evidence.accepted","visual":"one directional notch at closest approach","ui":"evidence +1, never combo","audio":"sfx.graze_evidence","haptic":"soft 8ms"},
    {"id":"cue.evidence.ready","event":"evidence.threshold.ready","visual":"local-void direction marker opens","ui":"evidence cell becomes available","audio":"sfx.evidence_ready","haptic":"two soft 10ms pulses"},
    {"id":"cue.override.charge","event":"override.charge.begin","visual":"directional gap grows only inside target radius","ui":"hold progress","audio":"sfx.override_charge","haptic":"ramp 15-35ms"},
    {"id":"cue.override.open","event":"localVoid.open","visual":"rule absent inside swept local region; no full-screen inversion in flash-off","ui":"evidence cell consumed","audio":"sfx.override_tear","haptic":"firm 45ms"},
    {"id":"cue.override.decay","event":"localVoid.decay.begin","visual":"digital gap closes from outside inward","ui":"none","audio":"sfx.override_void_decay","haptic":"none"},
    {"id":"cue.override.scar","event":"overrideScar.materialize","visual":"directional material fibers remain","ui":"memory +1","audio":"sfx.scar_write","haptic":"soft 18ms"},
    {"id":"cue.projectile.spawn","event":"projectile.armed","visual":"projectile body becomes collision-readable","ui":"none","audio":"sfx.projectile_arm","haptic":"none"},
    {"id":"cue.projectile.cancel","event":"projectile.cancel","visual":"digital body deletes, residue falls opposite velocity","ui":"none","audio":"sfx.projectile_cancel","haptic":"none"},
    {"id":"cue.projectile.impact","event":"projectile.impact","visual":"impact notch follows contact normal","ui":"none","audio":"sfx.projectile_impact","haptic":"soft 10ms"},
    {"id":"cue.player.damage","event":"player.damage","visual":"fiber tear; no collision inferred from frame","ui":"body interruption marker","audio":"sfx.player_damage","haptic":"firm 55ms"},
    {"id":"cue.player.collapse","event":"player.collapse","visual":"digital self deletes, death trace remains","ui":"run interruption strip","audio":"sfx.player_collapse","haptic":"firm 80ms then none"},
    {"id":"cue.player.return","event":"player.returnInput","visual":"flower resumes quiet breath with all rehydrated matter present","ui":"hud returns","audio":"sfx.player_return","haptic":"soft 20ms"},
    {"id":"cue.boss.phase","event":"boss.protocol.phaseChanged","visual":"topology rupture or re-route","ui":"protocol fact changes","audio":"boss.{bossId}.signal","haptic":"medium 32ms"},
    {"id":"cue.boss.resolution","event":"boss.resolution.commit","visual":"protocol-specific withdrawal and material remainder","ui":"resolution fact, no victory text","audio":"sfx.protocol_withdraw","haptic":"soft 30ms"},
    {"id":"cue.room.threshold","event":"room.threshold.commit","visual":"room-specific threshold cue","ui":"mental state label updates","audio":"sfx.room_threshold","haptic":"none"},
    {"id":"cue.cable.upload","event":"cable.upload.begin","visual":"packets move toward Eye","ui":"none","audio":"sfx.cable_upload","haptic":"none"},
    {"id":"cue.cable.burnin","event":"cable.burnIn.write","visual":"heat mark branches away from packet direction","ui":"memory group burn-in","audio":"sfx.cable_burnin","haptic":"none"},
    {"id":"cue.burnin.capture","event":"burnIn.capture","visual":"hard dots stay after camera turns","ui":"memory +1 only when serialized","audio":"sfx.burnin_capture","haptic":"soft 8ms"},
    {"id":"cue.ghost.begin","event":"ghost.replay.begin","visual":"actual route appears at captured first point","ui":"input held indicator","audio":"sfx.ghost_replay","haptic":"none"},
    {"id":"cue.ghost.end","event":"ghost.replay.complete","visual":"route extinguishes oldest-first","ui":"none","audio":"sfx.ghost_burnout","haptic":"soft 12ms"},
    {"id":"cue.witness.turn","event":"witness.turn","visual":"asynchronous turn toward committed source fact","ui":"none","audio":"sfx.witness_turn","haptic":"none"},
    {"id":"cue.snapshot.collect","event":"snapshot.collect","visual":"fingerprint builds from actual fact channels","ui":"snapshot panels open","audio":"sfx.snapshot_collect","haptic":"soft 18ms"},
    {"id":"cue.snapshot.handoff","event":"snapshot.handoff","visual":"fingerprint reduces to material seed","ui":"continue choices appear","audio":"sfx.snapshot_handoff","haptic":"soft 18ms"},
    {"id":"cue.noDusk","event":"noDusk.binaryTimeCut.begin","visual":"binary hard cut or threshold crawl in flash-off","ui":"weather/time fact","audio":"sfx.no_dusk_cut","haptic":"two firm 25ms pulses"},
    {"id":"cue.weather.static","event":"weather.STATIC.phase","visual":"static phase contract","ui":"weather phase when descriptions enabled","audio":"sfx.weather_static","haptic":"none"},
    {"id":"cue.weather.rain","event":"weather.RAIN.phase","visual":"rain phase contract","ui":"weather phase when descriptions enabled","audio":"sfx.weather_rain","haptic":"none"},
    {"id":"cue.weather.ash","event":"weather.ASH.phase","visual":"ash phase contract","ui":"weather phase when descriptions enabled","audio":"sfx.weather_ash","haptic":"none"},
    {"id":"cue.weather.wind","event":"weather.WIND.phase","visual":"wind phase contract","ui":"weather phase when descriptions enabled","audio":"sfx.weather_wind","haptic":"none"},
    {"id":"cue.weather.eclipse","event":"weather.ECLIPSE.phase","visual":"eclipse phase contract","ui":"weather phase when descriptions enabled","audio":"sfx.weather_eclipse","haptic":"medium 20ms at omen only"}
  ],
  "accessibility": {
    "reducedMotion":"Replace travel with representative poses; do not change cue event ticks.",
    "reduceFlash":"No full-screen inversion, no alternating luminance over 3Hz, no white-noise visual field.",
    "disableBinaural":"Render FORCED_ALIGNMENT spatial tension as mono amplitude beating at safe depth.",
    "hapticsOff":"Omit pulses without fallback delay.",
    "audioDescriptions":"Expose concise room, weather, gaze and material-memory state text."
  }
}
